Metadata-Version: 2.1
Name: eigoyurusan
Version: 0.1.7
Summary: English is too difficult for me.
Home-page: https://github.com/masora1030/eigoyurusan
Author: Sora Takashima
Author-email: soraemonpockt@gmail.com
License: MIT license
Project-URL: Projects, https://github.com/users/masora1030/projects/1
Project-URL: Source, https://github.com/masora1030/eigoyurusan
Keywords: eigoyurusan,translate,translator,paper,PDF
Platform: UNKNOWN
Classifier: Intended Audience :: Education
Classifier: Topic :: Text Processing :: Linguistic
Classifier: Development Status :: 3 - Alpha
Classifier: Programming Language :: Python :: 3
Classifier: License :: OSI Approved :: MIT License
Classifier: Operating System :: MacOS
